odoo/addons/l10n_th_gov_work_acceptance/README.rst
odoo/addons/l10n_th_gov_work_acceptance/__init__.py
odoo/addons/l10n_th_gov_work_acceptance/__manifest__.py
odoo/addons/l10n_th_gov_work_acceptance/data/evaluation_data.xml
odoo/addons/l10n_th_gov_work_acceptance/data/server_action.xml
odoo/addons/l10n_th_gov_work_acceptance/data/tier.definition.csv
odoo/addons/l10n_th_gov_work_acceptance/i18n/l10n_th_gov_work_acceptance.pot
odoo/addons/l10n_th_gov_work_acceptance/models/__init__.py
odoo/addons/l10n_th_gov_work_acceptance/models/purchase.py
odoo/addons/l10n_th_gov_work_acceptance/models/tier_validation.py
odoo/addons/l10n_th_gov_work_acceptance/models/work_acceptance.py
odoo/addons/l10n_th_gov_work_acceptance/models/work_acceptance_committee.py
odoo/addons/l10n_th_gov_work_acceptance/readme/CONTRIBUTORS.rst
odoo/addons/l10n_th_gov_work_acceptance/readme/DESCRIPTION.rst
odoo/addons/l10n_th_gov_work_acceptance/security/ir.model.access.csv
odoo/addons/l10n_th_gov_work_acceptance/static/description/icon.png
odoo/addons/l10n_th_gov_work_acceptance/static/description/index.html
odoo/addons/l10n_th_gov_work_acceptance/tests/__init__.py
odoo/addons/l10n_th_gov_work_acceptance/tests/test_gov_purchase_work_acceptance.py
odoo/addons/l10n_th_gov_work_acceptance/views/purchase_views.xml
odoo/addons/l10n_th_gov_work_acceptance/views/work_acceptance_views.xml
odoo14_addon_l10n_th_gov_work_acceptance-14.0.1.0.1.dev4.dist-info/METADATA
odoo14_addon_l10n_th_gov_work_acceptance-14.0.1.0.1.dev4.dist-info/WHEEL
odoo14_addon_l10n_th_gov_work_acceptance-14.0.1.0.1.dev4.dist-info/top_level.txt
odoo14_addon_l10n_th_gov_work_acceptance-14.0.1.0.1.dev4.dist-info/RECORD
