Metadata-Version: 2.1
Name: odoo14-addon-l10n-th-gov-work-acceptance
Version: 14.0.1.0.1.dev4
Summary: Thai Localization - Government Work Acceptance
Home-page: https://github.com/OCA/l10n-thailand
Author: Ecosoft, Odoo Community Association (OCA)
Author-email: support@odoo-community.org
License: AGPL-3
Platform: UNKNOWN
Classifier: Programming Language :: Python
Classifier: Framework :: Odoo
Classifier: Framework :: Odoo :: 14.0
Classifier: License :: OSI Approved :: GNU Affero General Public License v3
Classifier: Development Status :: 4 - Beta
Requires-Python: >=3.6
Requires-Dist: odoo14-addon-base-tier-validation-formula
Requires-Dist: odoo14-addon-base-tier-validation-forward
Requires-Dist: odoo14-addon-base-tier-validation-server-action
Requires-Dist: odoo14-addon-l10n-th-gov-purchase-request
Requires-Dist: odoo14-addon-purchase-work-acceptance-evaluation
Requires-Dist: odoo14-addon-purchase-work-acceptance-late-fines
Requires-Dist: odoo14-addon-purchase-work-acceptance-tier-validation
Requires-Dist: odoo <14.1dev,>=14.0a
